[
  {
    "id": "2024-pnw-loop",
    "name": "PNW Summer Loop 2024",
    "description": "Washington through Idaho into Montana and back via Glacier National Park.",
    "date": "2024-07-15",
    "tags": ["Washington", "Idaho", "Montana", "Alberta", "Glacier NP"],
    "color": "#3b82f6",
    "coordinates": [
      [47.6062, -122.3321],
      [47.7511, -120.7401],
      [47.4235, -120.3103],
      [47.7960, -118.0738],
      [47.6588, -117.4260],
      [47.6962, -116.7816],
      [47.6917, -116.3548],
      [47.5002, -115.9231],
      [46.8721, -114.0190],
      [47.0529, -113.5263],
      [48.2325, -113.9930],
      [48.4106, -113.9880],
      [48.6967, -113.7183],
      [48.7596, -113.7870],
      [49.0000, -113.4500],
      [49.0556, -113.4068],
      [48.7596, -113.7870],
      [48.4106, -113.9880],
      [47.6588, -117.4260],
      [47.7511, -120.7401],
      [47.6062, -122.3321]
    ]
  },
  {
    "id": "2022-canada-maritimes",
    "name": "Canada Maritimes 2022",
    "description": "Through Quebec into Newfoundland and back via Nova Scotia.",
    "date": "2022-08-10",
    "tags": ["Quebec", "Newfoundland", "Nova Scotia", "Gros Morne NP"],
    "color": "#ef4444",
    "coordinates": [
      [45.5017, -73.5673],
      [46.3432, -72.5421],
      [46.8139, -71.2080],
      [47.5615, -69.6317],
      [48.4476, -68.5214],
      [48.8267, -67.4685],
      [48.8566, -66.3757],
      [48.4889, -65.0000],
      [48.5052, -63.5000],
      [48.0000, -62.0000],
      [47.0000, -60.0000],
      [46.7684, -56.1771],
      [47.5000, -56.0000],
      [48.5000, -56.5000],
      [49.2000, -57.5000],
      [49.7100, -57.9000],
      [49.2000, -57.5000],
      [48.5000, -56.5000],
      [47.5000, -56.0000],
      [46.7684, -56.1771],
      [46.0000, -60.0000],
      [45.6000, -61.3600],
      [44.6488, -63.5752],
      [44.3500, -64.2500],
      [45.5017, -73.5673]
    ]
  },
  {
    "id": "2025-summer-pct",
    "name": "West Coast Summer 2025",
    "description": "Down the Pacific coast from Washington through Oregon to California.",
    "date": "2025-06-20",
    "tags": ["Washington", "Oregon", "California", "Redwoods", "Olympic NP", "Crater Lake"],
    "color": "#22c55e",
    "coordinates": [
      [47.6062, -122.3321],
      [47.8979, -123.0996],
      [47.8601, -124.0752],
      [46.9741, -124.0048],
      [46.1879, -123.8313],
      [45.5152, -122.6784],
      [44.9429, -123.0351],
      [44.0582, -121.3153],
      [42.8684, -122.1685],
      [42.4425, -122.7141],
      [42.0000, -124.2000],
      [41.7558, -124.2026],
      [41.2132, -124.0046],
      [40.7865, -124.1637],
      [39.7285, -123.8053],
      [38.9072, -123.4787],
      [38.3047, -122.4792],
      [37.7749, -122.4194]
    ]
  }
]
